git_ai_tools/__init__.py
git_ai_tools/cli.py
git_ai_tools/core.py
git_ai_tools-0.1.1.dist-info/LICENSE
git_ai_tools-0.1.1.dist-info/METADATA
git_ai_tools-0.1.1.dist-info/WHEEL
git_ai_tools-0.1.1.dist-info/entry_points.txt
git_ai_tools-0.1.1.dist-info/top_level.txt
git_ai_tools-0.1.1.dist-info/RECORD
