Metadata-Version: 2.2
Name: git-ai-tools
Version: 0.1.1
Summary: A collection of AI-powered Git tools
Home-page: https://github.com/mik1337/git-ai-tools
Author: Mik
Author-email: workwithme@mik.sh
Classifier: Programming Language :: Python :: 3
Classifier: License :: OSI Approved :: MIT License
Classifier: Operating System :: OS Independent
Requires-Python: >=3.8
License-File: LICENSE
Requires-Dist: gitpython>=3.1.42
Requires-Dist: click>=8.1.7
Requires-Dist: requests>=2.31.0
Dynamic: author
Dynamic: author-email
Dynamic: classifier
Dynamic: description
Dynamic: description-content-type
Dynamic: home-page
Dynamic: requires-dist
Dynamic: requires-python
Dynamic: summary
